corgi/__init__.py
corgi/_org.py
corgi/agenda.py
corgi/ansi.py
corgi/app.py
corgi/args.py
corgi/config.py
corgi/format.py
corgi/functional.py
corgi/lick/__init__.py
corgi/lick/elements.py
corgi/lick/jsonizer.py
corgi/lick/node.py
corgi/lick/parser.py
corgi/node_predicates.py
corgi/org.py
corgi/theme.py
corgi/utils.py
corgi_org_tool-0.1.0.dist-info/entry_points.txt
corgi_org_tool-0.1.0.dist-info/LICENSE
corgi_org_tool-0.1.0.dist-info/WHEEL
corgi_org_tool-0.1.0.dist-info/METADATA
corgi_org_tool-0.1.0.dist-info/RECORD
