Metadata-Version: 2.1
Name: corgi-org-tool
Version: 0.1.0
Summary: Command Line parser, agenda and manipulator for org-mode files.
Home-page: https://git.goral.net.pl/mgoral/corgi
License: GPLv3
Author: Michal Goral
Author-email: dev@goral.net.pl
Requires-Python: >=3.8,<4.0
Classifier: Development Status :: 3 - Alpha
Classifier: Environment :: Console
Classifier: Intended Audience :: End Users/Desktop
Classifier: License :: OSI Approved :: GNU General Public License v3 (GPLv3)
Classifier: License :: Other/Proprietary License
Classifier: Natural Language :: English
Classifier: Operating System :: POSIX
Classifier: Programming Language :: Python :: 3
Classifier: Programming Language :: Python :: 3.8
Classifier: Programming Language :: Python :: 3.9
Classifier: Programming Language :: Python :: 3.10
Classifier: Topic :: Office/Business :: Scheduling
Classifier: Topic :: Text Processing
Classifier: Topic :: Utilities
Requires-Dist: colorama (>=0.4.4,<0.5.0)
Requires-Dist: tomli (>=2.0.1,<3.0.0)
Project-URL: Repository, https://git.goral.net.pl/mgoral/corgi
